LICENSE
README.rst
manual_requirements.txt
requirements.txt
setup.py
n225/__init__.py
n225/__main__.py
n225/jpx.py
n225.egg-info/PKG-INFO
n225.egg-info/SOURCES.txt
n225.egg-info/dependency_links.txt
n225.egg-info/requires.txt
n225.egg-info/top_level.txt
n225/data/initial_n225.csv
n225/data/n225.csv